{"stat.flyOneCm":179473,"stat.walkOneCm":21630,"stat.jump":51,"stat.swimOneCm":6489,"stat.pickup.minecraft.egg":1,"stat.playOneMinute":14430,"stat.killEntity.Chicken":10,"stat.useItem.minecraft.egg":248,"stat.useItem.minecraft.snowball":449,"stat.sneakTime":1488,"stat.pickup.minecraft.feather":3,"stat.damageDealt":421,"stat.crouchOneCm":2437,"stat.pickup.minecraft.chicken":2,"stat.timeSinceDeath":14430,"stat.sprintOneCm":6937,"stat.mobKills":10,"stat.useItem.minecraft.stone_slab2":116,"stat.useItem.minecraft.spawn_egg":4,"stat.diveOneCm":9035,"stat.useItem.minecraft.diamond_sword":11,"stat.useItem.minecraft.water_bucket":31,"stat.craftingTableInteraction":1}